gpcrmining/__init__.py
gpcrmining/gpcrdb/__init__.py
gpcrmining/gpcrdb/__main__.py
gpcrmining/gpcrdb/sequence.py
gpcrmining/gpcrdb/structure.py
gpcrmining-0.2.0.dist-info/LICENSE
gpcrmining-0.2.0.dist-info/METADATA
gpcrmining-0.2.0.dist-info/WHEEL
gpcrmining-0.2.0.dist-info/top_level.txt
gpcrmining-0.2.0.dist-info/RECORD
